dataart_python/__init__.py
dataart_python/client.py
dataart_python/container.py
dataart_python/request.py
dataart_python/timer.py
dataart_python/uploader.py
dataart_python/worker.py
dataart_python-0.1.0.dist-info/entry_points.txt
dataart_python-0.1.0.dist-info/LICENSE
dataart_python-0.1.0.dist-info/WHEEL
dataart_python-0.1.0.dist-info/METADATA
dataart_python-0.1.0.dist-info/RECORD
