Metadata-Version: 2.1
Name: dataart-python
Version: 0.1.0
Summary: 
License: MIT
Author: sadra khamoshi
Author-email: sadrakhamoshi7@gmail.com
Requires-Python: >=3.7,<4.0
Classifier: License :: OSI Approved :: MIT License
Classifier: Programming Language :: Python :: 3
Classifier: Programming Language :: Python :: 3.10
Classifier: Programming Language :: Python :: 3.7
Classifier: Programming Language :: Python :: 3.8
Classifier: Programming Language :: Python :: 3.9
Requires-Dist: requests (==2.27.1)
